brain/__init__.py
brain/blue_print.py
pybrain_pkg_dewmal-0.0.1.dist-info/LICENSE
pybrain_pkg_dewmal-0.0.1.dist-info/METADATA
pybrain_pkg_dewmal-0.0.1.dist-info/WHEEL
pybrain_pkg_dewmal-0.0.1.dist-info/top_level.txt
pybrain_pkg_dewmal-0.0.1.dist-info/RECORD
